{
  "id": "uLGJkpEM8SyzFVEm",
  "name": "AutoMagicly - Audit Email Results",
  "nodes": [
    {
      "parameters": {
        "httpMethod": "POST",
        "path": "audit-email-results",
        "authentication": "headerAuth",
        "responseMode": "responseNode",
        "options": {}
      },
      "name": "Webhook - Email Results",
      "type": "n8n-nodes-base.webhook",
      "typeVersion": 2,
      "position": [
        208,
        288
      ],
      "webhookId": "automagicly-audit-email-results",
      "credentials": {
        "httpHeaderAuth": {
          "id": "4p35NhehjSnmQLI0",
          "name": "AutoMagicly Chat API Key"
        }
      }
    },
    {
      "parameters": {
        "conditions": {
          "options": {
            "caseSensitive": true,
            "leftValue": "",
            "typeValidation": "strict",
            "version": 1
          },
          "conditions": [
            {
              "id": "condition-sessionId",
              "leftValue": "={{ $json.body.sessionId }}",
              "rightValue": "",
              "operator": {
                "type": "string",
                "operation": "exists",
                "singleValue": true
              }
            },
            {
              "id": "condition-email",
              "leftValue": "={{ $json.body.email }}",
              "rightValue": "",
              "operator": {
                "type": "string",
                "operation": "exists",
                "singleValue": true
              }
            }
          ],
          "combinator": "and"
        },
        "options": {}
      },
      "name": "Validate Input",
      "type": "n8n-nodes-base.if",
      "typeVersion": 2,
      "position": [
        432,
        288
      ]
    },
    {
      "parameters": {
        "respondWith": "json",
        "responseBody": "={{ { \"error\": \"Invalid request. Please provide 'sessionId' and 'email'.\", \"success\": false } }}",
        "options": {
          "responseCode": 400
        }
      },
      "name": "Return Validation Error",
      "type": "n8n-nodes-base.respondToWebhook",
      "typeVersion": 1,
      "position": [
        656,
        384
      ]
    },
    {
      "parameters": {
        "jsCode": "// Format the email HTML with pain points and recommendations\nconst data = $input.first().json.body;\n\n// Build pain points HTML\nlet painPointsHtml = '';\nif (data.painPoints && data.painPoints.length > 0) {\n  painPointsHtml = data.painPoints.map(pp => \n    `<div style=\"background: #fef3c7; padding: 12px 16px; border-radius: 8px; margin: 8px 0; border-left: 4px solid #f59e0b;\">\n      <strong style=\"color: #92400e;\">${pp.category}</strong>\n      <p style=\"margin: 4px 0 0 0; color: #78350f;\">${pp.description}</p>\n      <span style=\"display: inline-block; margin-top: 8px; padding: 2px 8px; border-radius: 12px; font-size: 12px; background: ${pp.severity === 'high' ? '#fecaca' : pp.severity === 'medium' ? '#fed7aa' : '#d1fae5'}; color: ${pp.severity === 'high' ? '#991b1b' : pp.severity === 'medium' ? '#c2410c' : '#065f46'};\">${pp.severity} priority</span>\n    </div>`\n  ).join('');\n}\n\n// Build recommendations HTML\nlet recommendationsHtml = '';\nif (data.recommendations && data.recommendations.length > 0) {\n  recommendationsHtml = data.recommendations.map((rec, i) => \n    `<div style=\"border: 1px solid #e5e7eb; padding: 20px; border-radius: 12px; margin: 12px 0;\">\n      <div style=\"display: flex; align-items: center; gap: 12px; margin-bottom: 12px;\">\n        <span style=\"background: #3b82f6; color: white; width: 28px; height: 28px; border-radius: 50%; display: inline-flex; align-items: center; justify-content: center; font-weight: bold;\">${i + 1}</span>\n        <h3 style=\"margin: 0; color: #1f2937; font-size: 18px;\">${rec.title}</h3>\n      </div>\n      <p style=\"margin: 0 0 12px 0; color: #4b5563;\">${rec.description}</p>\n      <div style=\"display: flex; gap: 8px; flex-wrap: wrap;\">\n        <span style=\"padding: 4px 12px; border-radius: 16px; font-size: 12px; background: #dbeafe; color: #1e40af;\">Complexity: ${rec.complexity}</span>\n        ${rec.estimatedROI ? `<span style=\"padding: 4px 12px; border-radius: 16px; font-size: 12px; background: #dcfce7; color: #166534;\">ROI: ${rec.estimatedROI}</span>` : ''}\n      </div>\n    </div>`\n  ).join('');\n}\n\nconst emailHtml = `<!DOCTYPE html>\n<html>\n<head>\n  <meta name=\"viewport\" content=\"width=device-width, initial-scale=1.0\">\n</head>\n<body style=\"margin: 0; padding: 0; font-family: -apple-system, BlinkMacSystemFont, 'Segoe UI', Arial, sans-serif; background-color: #f3f4f6;\">\n  <div style=\"max-width: 600px; margin: 0 auto; padding: 20px;\">\n    <div style=\"background: white; border-radius: 16px; overflow: hidden; box-shadow: 0 4px 6px rgba(0,0,0,0.1);\">\n      \n      <!-- Header -->\n      <div style=\"background: linear-gradient(135deg, #3b82f6 0%, #8b5cf6 100%); color: white; padding: 40px 30px; text-align: center;\">\n        <h1 style=\"margin: 0; font-size: 28px; font-weight: 700;\">Your AI Business Audit Results</h1>\n        <p style=\"margin: 10px 0 0 0; font-size: 16px; opacity: 0.9;\">We found ${data.recommendations?.length || 0} opportunities to automate your business</p>\n      </div>\n\n      <!-- Content -->\n      <div style=\"padding: 30px;\">\n        <p style=\"font-size: 16px; color: #374151;\">Hi ${data.name || 'there'},</p>\n        <p style=\"font-size: 16px; color: #374151;\">Thank you for completing our AI Business Audit! Based on your responses, we've identified several areas where automation could save you time and streamline your operations.</p>\n        \n        <!-- Pain Points Section -->\n        ${painPointsHtml ? `\n        <h2 style=\"color: #1f2937; font-size: 20px; margin: 30px 0 16px 0; border-bottom: 2px solid #e5e7eb; padding-bottom: 8px;\">Challenges Identified</h2>\n        ${painPointsHtml}\n        ` : ''}\n        \n        <!-- Recommendations Section -->\n        ${recommendationsHtml ? `\n        <h2 style=\"color: #1f2937; font-size: 20px; margin: 30px 0 16px 0; border-bottom: 2px solid #e5e7eb; padding-bottom: 8px;\">Recommended Solutions</h2>\n        ${recommendationsHtml}\n        ` : ''}\n        \n        <!-- Next Steps -->\n        ${data.nextSteps ? `\n        <div style=\"background: #eff6ff; padding: 20px; border-radius: 12px; margin: 30px 0;\">\n          <h3 style=\"color: #1e40af; margin: 0 0 8px 0;\">Next Steps</h3>\n          <p style=\"color: #1e3a8a; margin: 0;\">${data.nextSteps}</p>\n        </div>\n        ` : ''}\n        \n        <!-- CTA Button -->\n        <div style=\"text-align: center; margin: 30px 0;\">\n          <a href=\"https://automagicly.ai/#booking\" style=\"display: inline-block; background: linear-gradient(135deg, #3b82f6 0%, #8b5cf6 100%); color: white; padding: 16px 32px; border-radius: 12px; text-decoration: none; font-weight: 600; font-size: 16px;\">Book Your Free Consultation</a>\n          <p style=\"color: #6b7280; font-size: 14px; margin-top: 12px;\">Let's discuss how to implement these recommendations</p>\n        </div>\n        \n        <hr style=\"border: none; border-top: 1px solid #e5e7eb; margin: 30px 0;\">\n        \n        <p style=\"color: #6b7280; font-size: 14px; text-align: center;\">Questions? Reply to this email or visit <a href=\"https://automagicly.ai\" style=\"color: #3b82f6;\">automagicly.ai</a></p>\n      </div>\n      \n      <!-- Footer -->\n      <div style=\"background: #f9fafb; padding: 20px 30px; text-align: center;\">\n        <p style=\"color: #9ca3af; font-size: 12px; margin: 0;\">© ${new Date().getFullYear()} AutoMagicly. All rights reserved.</p>\n      </div>\n    </div>\n  </div>\n</body>\n</html>`;\n\nreturn {\n  json: {\n    email: data.email,\n    name: data.name,\n    sessionId: data.sessionId,\n    recommendationCount: data.recommendations?.length || 0,\n    emailHtml: emailHtml\n  }\n};"
      },
      "name": "Format Email HTML",
      "type": "n8n-nodes-base.code",
      "typeVersion": 2,
      "position": [
        656,
        192
      ]
    },
    {
      "parameters": {
        "sendTo": "rashad.barnett@gmail.com",
        "subject": "=Your AI Business Audit Results - {{ $json.recommendationCount }} Opportunities Found",
        "message": "={{ $json.emailHtml }}",
        "options": {}
      },
      "name": "Send Email",
      "type": "n8n-nodes-base.gmail",
      "typeVersion": 2.1,
      "position": [
        880,
        192
      ],
      "webhookId": "074e3539-82f4-4de6-a90c-53f15dea4853",
      "credentials": {
        "gmailOAuth2": {
          "id": "BTKh5C4ujrbOxvPI",
          "name": "Rashad.barnett@gmail.com"
        }
      }
    },
    {
      "parameters": {
        "respondWith": "json",
        "responseBody": "={{ { \"success\": true, \"message\": \"Email sent successfully\", \"email\": $json.email } }}",
        "options": {}
      },
      "name": "Return Success",
      "type": "n8n-nodes-base.respondToWebhook",
      "typeVersion": 1,
      "position": [
        1104,
        192
      ]
    }
  ],
  "connections": {
    "Webhook - Email Results": {
      "main": [
        [
          {
            "node": "Validate Input",
            "type": "main",
            "index": 0
          }
        ]
      ]
    },
    "Validate Input": {
      "main": [
        [
          {
            "node": "Format Email HTML",
            "type": "main",
            "index": 0
          }
        ],
        [
          {
            "node": "Return Validation Error",
            "type": "main",
            "index": 0
          }
        ]
      ]
    },
    "Format Email HTML": {
      "main": [
        [
          {
            "node": "Send Email",
            "type": "main",
            "index": 0
          }
        ]
      ]
    },
    "Send Email": {
      "main": [
        [
          {
            "node": "Return Success",
            "type": "main",
            "index": 0
          }
        ]
      ]
    }
  },
  "settings": {
    "saveDataSuccessExecution": "all",
    "executionTimeout": 3600,
    "timezone": "UTC"
  },
  "tags": [],
  "active": true
}